 16           0 LOAD_CONST               1 (0)
              2 STORE_FAST               0 (overall_sum)

 17           4 LOAD_GLOBAL              0 (range)
              6 LOAD_GLOBAL              1 (ROWS)
              8 CALL_FUNCTION            1
             10 GET_ITER
        >>   12 FOR_ITER                13 (to 40)
             14 STORE_FAST               1 (row)

 18          16 LOAD_GLOBAL              0 (range)
             18 LOAD_GLOBAL              2 (COLUMNS)
             20 CALL_FUNCTION            1
             22 GET_ITER
        >>   24 FOR_ITER                 6 (to 38)
             26 STORE_FAST               2 (column)

 19          28 LOAD_FAST                0 (overall_sum)
             30 LOAD_CONST               2 (1)
             32 INPLACE_ADD
             34 STORE_FAST               0 (overall_sum)
             36 JUMP_ABSOLUTE           12 (to 24)

 18     >>   38 JUMP_ABSOLUTE            6 (to 12)

 17     >>   40 LOAD_CONST               0 (None)
             42 RETURN_VALUE
None
